deep_index/__init__.py
deep_index/liblicense.a
deep_index-1.0.0.dist-info/METADATA
deep_index-1.0.0.dist-info/WHEEL
deep_index-1.0.0.dist-info/top_level.txt
deep_index-1.0.0.dist-info/RECORD
