Metadata-Version: 2.1
Name: deep-index
Version: 1.0.0
Summary: Deep-Index is DeepGPU/DeepNCCL/DeepyTorch's root_path.
Home-page: https://help.aliyun.com/document_detail/462422.html?spm=a2c4g.462031.0.0.c5f96b4drcx52F
Author: Alibaba Cloud
Author-email: ziqi.yzq@alibaba-inc.com
License: Copyright (C) Alibaba Group Holding Limited
Keywords: Distributed,Deep Learning,Communication,NCCL,AIACC,DeepGPU,DeepNCCL,DeepyTorch
Platform: UNKNOWN
Requires-Python: >=3.0
